opencortex/__init__.py
opencortex/__main__.py
opencortex/application.py
opencortex/config/Default.yaml
opencortex/config/ERP.yaml
opencortex/config/__init__.py
opencortex/neuroengine/__init__.py
opencortex/neuroengine/_old.py
opencortex/neuroengine/base_model.py
opencortex/neuroengine/classifier.py
opencortex/neuroengine/setup_dialog.py
opencortex/neuroengine/streamer_gui.py
opencortex/neuroengine/core/__init__.py
opencortex/neuroengine/core/stream_engine.py
opencortex/neuroengine/flux/__init__.py
opencortex/neuroengine/flux/band_power.py
opencortex/neuroengine/flux/base.py
opencortex/neuroengine/flux/quality_estimator.py
opencortex/neuroengine/gui/__init__.py
opencortex/neuroengine/gui/eeg_map_widget.py
opencortex/neuroengine/gui/frequency_band_widget.py
opencortex/neuroengine/gui/gui_adapter.py
opencortex/neuroengine/gui/streamer_gui_service.py
opencortex/neuroengine/models/__init__.py
opencortex/neuroengine/models/onnx_model.py
opencortex/neuroengine/models/pytorch_model.py
opencortex/neuroengine/models/sklearn_model.py
opencortex/neuroengine/models/classification/__init__.py
opencortex/neuroengine/models/classification/majority_vote.py
opencortex/neuroengine/network/__init__.py
opencortex/neuroengine/network/lsl_stream.py
opencortex/neuroengine/network/osc_stream.py
opencortex/neuroengine/test/__init__.py
opencortex/neuroengine/test/classifier_test.py
opencortex/processing/__init__.py
opencortex/processing/preprocessing.py
opencortex/processing/proc_helper.py
opencortex/utils/__init__.py
opencortex/utils/layouts.py
opencortex/utils/loader.py
opencortex/utils/net_utils.py
opencortex/validation/__init__.py
opencortex/validation/cross_val.py
test/__init__.py
test/classifier_test.py
test/streamer_test.py
test/test_headless.py
opencortex-0.1.7.post1.dist-info/LICENSE
opencortex-0.1.7.post1.dist-info/METADATA
opencortex-0.1.7.post1.dist-info/WHEEL
opencortex-0.1.7.post1.dist-info/entry_points.txt
opencortex-0.1.7.post1.dist-info/top_level.txt
opencortex-0.1.7.post1.dist-info/RECORD
