Metadata-Version: 2.1
Name: opencortex
Version: 0.1.7.post1
Summary: Software to stream EEG data, perform preprocessing, and train machine learning models to build real-time BCI applications.
Home-page: https://github.com/BRomans/OpenCortex
Author: Michele Romani
Author-email: Michele Romani <michele.romani.gzl0@gmail.com>
Project-URL: Homepage, https://github.com/BRomans/OpenCortex
Project-URL: Issues, https://github.com/BRomans/OpenCortex/issues
Classifier: Programming Language :: Python :: 3
Classifier: License :: OSI Approved :: GNU General Public License v3 (GPLv3)
Classifier: Operating System :: OS Independent
Requires-Python: >=3.8
License-File: LICENSE
Requires-Dist: pandas ~=2.2.0
Requires-Dist: numpy <2.0
Requires-Dist: pyarrow
Requires-Dist: python-osc ~=1.9.0
Requires-Dist: pylsl ~=1.16.2
Requires-Dist: pybluez2
Requires-Dist: pyserial ~=3.5
Requires-Dist: mne ~=1.6.1
Requires-Dist: brainflow ~=5.18.0
Requires-Dist: scikit-learn >=1.5.0
Requires-Dist: onnxruntime >=1.20.1
Requires-Dist: torch >=2.5.0
Requires-Dist: matplotlib >=3.8.2
Requires-Dist: seaborn ~=0.13.2
Requires-Dist: imblearn ~=0.0
Requires-Dist: PyQt5 >=5.15.7
Requires-Dist: PyQt5-Qt5 >=5.15.2
Requires-Dist: PyQt5-sip >=12.11.0
Requires-Dist: pyqtgraph >=0.12.4
Requires-Dist: future ~=1.0.0
Requires-Dist: setuptools ~=70.0.0
Requires-Dist: PyYAML ~=6.0.1
Requires-Dist: joblib ~=1.3.2
